r2d2_pal-0.1.11.dist-info/METADATA
r2d2_pal-0.1.11.dist-info/WHEEL
r2d2_pal-0.1.11.dist-info/licenses/LICENSE
r2d2/__init__.py
r2d2/r2d2.abi3.so
r2d2_pal-0.1.11.dist-info/RECORD
