Metadata-Version: 2.3
Name: r2d2-pal
Version: 0.1.11
Classifier: Programming Language :: Rust
Classifier: Programming Language :: Python :: Implementation :: CPython
Classifier: Programming Language :: Python :: Implementation :: PyPy
License-File: LICENSE
Summary: An I/O device communication module written in Rust.
License: MIT License
Requires-Python: >=3.8
